{
  "id": "3e611198-f41d-4363-8f33-10e0b697cded",
  "prevId": "33d6a9de-0d3b-4147-84c3-e6bea1d6388c",
  "version": "7",
  "dialect": "postgresql",
  "tables": {
    "public.persona": {
      "name": "persona",
      "schema": "",
      "columns": {
        "id": {
          "name": "id",
          "type": "uuid",
          "primaryKey": true,
          "notNull": true
        },
        "nombre": {
          "name": "nombre",
          "type": "text",
          "primaryKey": false,
          "notNull": true
        },
        "creado_en": {
          "name": "creado_en",
          "type": "timestamp with time zone",
          "primaryKey": false,
          "notNull": true
        },
        "actualizado_en": {
          "name": "actualizado_en",
          "type": "timestamp with time zone",
          "primaryKey": false,
          "notNull": true
        }
      },
      "indexes": {},
      "foreignKeys": {},
      "compositePrimaryKeys": {},
      "uniqueConstraints": {},
      "policies": {},
      "checkConstraints": {},
      "isRLSEnabled": false
    },
    "public.sesion": {
      "name": "sesion",
      "schema": "",
      "columns": {
        "id": {
          "name": "id",
          "type": "uuid",
          "primaryKey": true,
          "notNull": true
        },
        "token_hash": {
          "name": "token_hash",
          "type": "text",
          "primaryKey": false,
          "notNull": true
        },
        "usuario_id": {
          "name": "usuario_id",
          "type": "uuid",
          "primaryKey": false,
          "notNull": true
        },
        "usuario_real_id": {
          "name": "usuario_real_id",
          "type": "uuid",
          "primaryKey": false,
          "notNull": true
        },
        "creado_en": {
          "name": "creado_en",
          "type": "timestamp with time zone",
          "primaryKey": false,
          "notNull": true
        },
        "actualizado_en": {
          "name": "actualizado_en",
          "type": "timestamp with time zone",
          "primaryKey": false,
          "notNull": true
        },
        "expira_en": {
          "name": "expira_en",
          "type": "timestamp with time zone",
          "primaryKey": false,
          "notNull": true
        }
      },
      "indexes": {
        "sesion_token_hash_unique": {
          "name": "sesion_token_hash_unique",
          "columns": [
            {
              "expression": "token_hash",
              "isExpression": false,
              "asc": true,
              "nulls": "last"
            }
          ],
          "isUnique": true,
          "concurrently": false,
          "method": "btree",
          "with": {}
        }
      },
      "foreignKeys": {
        "sesion_usuario_id_usuario_id_fk": {
          "name": "sesion_usuario_id_usuario_id_fk",
          "tableFrom": "sesion",
          "tableTo": "usuario",
          "columnsFrom": [
            "usuario_id"
          ],
          "columnsTo": [
            "id"
          ],
          "onDelete": "cascade",
          "onUpdate": "no action"
        },
        "sesion_usuario_real_id_usuario_id_fk": {
          "name": "sesion_usuario_real_id_usuario_id_fk",
          "tableFrom": "sesion",
          "tableTo": "usuario",
          "columnsFrom": [
            "usuario_real_id"
          ],
          "columnsTo": [
            "id"
          ],
          "onDelete": "cascade",
          "onUpdate": "no action"
        }
      },
      "compositePrimaryKeys": {},
      "uniqueConstraints": {},
      "policies": {},
      "checkConstraints": {},
      "isRLSEnabled": false
    },
    "public.usuario": {
      "name": "usuario",
      "schema": "",
      "columns": {
        "id": {
          "name": "id",
          "type": "uuid",
          "primaryKey": true,
          "notNull": true
        },
        "persona_id": {
          "name": "persona_id",
          "type": "uuid",
          "primaryKey": false,
          "notNull": true
        },
        "email": {
          "name": "email",
          "type": "text",
          "primaryKey": false,
          "notNull": true
        },
        "password_hash": {
          "name": "password_hash",
          "type": "text",
          "primaryKey": false,
          "notNull": true
        },
        "rol": {
          "name": "rol",
          "type": "rol_usuario",
          "typeSchema": "public",
          "primaryKey": false,
          "notNull": true
        },
        "creado_en": {
          "name": "creado_en",
          "type": "timestamp with time zone",
          "primaryKey": false,
          "notNull": true
        },
        "actualizado_en": {
          "name": "actualizado_en",
          "type": "timestamp with time zone",
          "primaryKey": false,
          "notNull": true
        }
      },
      "indexes": {
        "usuario_email_unique": {
          "name": "usuario_email_unique",
          "columns": [
            {
              "expression": "email",
              "isExpression": false,
              "asc": true,
              "nulls": "last"
            }
          ],
          "isUnique": true,
          "concurrently": false,
          "method": "btree",
          "with": {}
        }
      },
      "foreignKeys": {
        "usuario_persona_id_persona_id_fk": {
          "name": "usuario_persona_id_persona_id_fk",
          "tableFrom": "usuario",
          "tableTo": "persona",
          "columnsFrom": [
            "persona_id"
          ],
          "columnsTo": [
            "id"
          ],
          "onDelete": "restrict",
          "onUpdate": "no action"
        }
      },
      "compositePrimaryKeys": {},
      "uniqueConstraints": {
        "usuario_persona_id_unique": {
          "name": "usuario_persona_id_unique",
          "nullsNotDistinct": false,
          "columns": [
            "persona_id"
          ]
        }
      },
      "policies": {},
      "checkConstraints": {},
      "isRLSEnabled": false
    }
  },
  "enums": {
    "public.rol_usuario": {
      "name": "rol_usuario",
      "schema": "public",
      "values": [
        "administrador",
        "miembro"
      ]
    }
  },
  "schemas": {},
  "sequences": {},
  "roles": {},
  "policies": {},
  "views": {},
  "_meta": {
    "columns": {},
    "schemas": {},
    "tables": {}
  }
}